datanavigator/__init__.py
datanavigator/__version__.py
datanavigator/_config.py
datanavigator/assets.py
datanavigator/components.py
datanavigator/core.py
datanavigator/events.py
datanavigator/examples.py
datanavigator/opticalflow.py
datanavigator/plots.py
datanavigator/pointtracking.py
datanavigator/signals.py
datanavigator/utils.py
datanavigator/videos.py
datanavigator-1.1.4.dist-info/LICENSE
datanavigator-1.1.4.dist-info/WHEEL
datanavigator-1.1.4.dist-info/METADATA
datanavigator-1.1.4.dist-info/RECORD
