Metadata-Version: 2.1
Name: datanavigator
Version: 1.1.4
Summary: Interactive data visualization for signals, videos, and complex data objects.
Keywords: data,visualization,analysis,time series,video,images,scientific
Author-email: Praneeth Namburi <praneeth.namburi@gmail.com>
Requires-Python: >=3.7
Classifier: Development Status :: 5 - Production/Stable
Classifier: License :: OSI Approved :: MIT License
Classifier: Topic :: Scientific/Engineering
Classifier: Programming Language :: Python
Classifier: Programming Language :: Python :: 3.7
Classifier: Programming Language :: Python :: 3.8
Classifier: Programming Language :: Python :: 3.9
Classifier: Programming Language :: Python :: 3.10
Classifier: Programming Language :: Python :: 3.11
Classifier: Programming Language :: Python :: 3.12
Classifier: Programming Language :: Python :: Implementation :: CPython
Classifier: Programming Language :: Python :: Implementation :: PyPy
Requires-Dist: numpy<2
Requires-Dist: pandas
Requires-Dist: matplotlib
Requires-Dist: opencv-python
Requires-Dist: portion
Requires-Dist: ffmpeg-python
Requires-Dist: pysampled
Requires-Dist: decord
Requires-Dist: tables
Requires-Dist: tqdm
Project-URL: Documentation, https://datanavigator.readthedocs.io/
Project-URL: Home, https://github.com/praneethnamburi/datanavigator
Project-URL: Issues, https://github.com/praneethnamburi/datanavigator/issues
Project-URL: Repository, https://github.com/praneethnamburi/datanavigator
